{
  "config": "{\"version\":\"5.59\",\"themeCollection\":{\"baseTheme\":{\"name\":\"CY24SU10\",\"version\":\"5.59\",\"type\":2}},\"activeSectionIndex\":0,\"defaultDrillFilterOtherVisuals\":true,\"linguisticSchemaSyncVersion\":0,\"settings\":{\"useNewFilterPaneExperience\":true,\"allowChangeFilterTypes\":true,\"useStylableVisualContainerHeader\":true,\"queryLimitOption\":6,\"exportDataMode\":1,\"useDefaultAggregateDisplayName\":true,\"useEnhancedTooltips\":true},\"objects\":{\"section\":[{\"properties\":{\"verticalAlignment\":{\"expr\":{\"Literal\":{\"Value\":\"'Top'\"}}}}}],\"outspacePane\":[{\"properties\":{\"expanded\":{\"expr\":{\"Literal\":{\"Value\":\"false\"}}}}}]}}",
  "layoutOptimization": 0,
  "resourcePackages": [
    {
      "resourcePackage": {
        "disabled": false,
        "items": [
          {
            "name": "CY24SU10",
            "path": "BaseThemes/CY24SU10.json",
            "type": 202
          }
        ],
        "name": "SharedResources",
        "type": 2
      }
    }
  ],
  "sections": [
    {
      "config": "{}",
      "displayName": "Page 1",
      "displayOption": 1,
      "filters": "[]",
      "height": 720.00,
      "name": "34f938de57018de7068a",
      "visualContainers": [
        {
          "config": "{\"name\":\"8b6deee90c9124c06c80\",\"layouts\":[{\"id\":0,\"position\":{\"x\":9.448891554591802,\"y\":39.68534452928557,\"z\":1000,\"width\":508.350365637039,\"height\":111.49692034418327,\"tabOrder\":1000}}],\"singleVisual\":{\"visualType\":\"slicer\",\"projections\":{\"Values\":[{\"queryRef\":\"earthquake_events_gold.time\",\"active\":true}]},\"prototypeQuery\":{\"Version\":2,\"From\":[{\"Name\":\"e\",\"Entity\":\"earthquake_events_gold\",\"Type\":0}],\"Select\":[{\"Column\":{\"Expression\":{\"SourceRef\":{\"Source\":\"e\"}},\"Property\":\"time\"},\"Name\":\"earthquake_events_gold.time\",\"NativeReferenceName\":\"time\"}],\"OrderBy\":[{\"Direction\":1,\"Expression\":{\"Column\":{\"Expression\":{\"SourceRef\":{\"Source\":\"e\"}},\"Property\":\"time\"}}}]},\"drillFilterOtherVisuals\":true,\"hasDefaultSort\":true,\"objects\":{\"data\":[{\"properties\":{\"mode\":{\"expr\":{\"Literal\":{\"Value\":\"'Between'\"}}}}}],\"header\":[{\"properties\":{\"text\":{\"expr\":{\"Literal\":{\"Value\":\"'TimeFrame'\"}}},\"show\":{\"expr\":{\"Literal\":{\"Value\":\"false\"}}}}}],\"general\":[{\"properties\":{\"orientation\":{\"expr\":{\"Literal\":{\"Value\":\"1D\"}}}}}]},\"vcObjects\":{\"title\":[{\"properties\":{\"text\":{\"expr\":{\"Literal\":{\"Value\":\"'TimeFrame'\"}}},\"show\":{\"expr\":{\"Literal\":{\"Value\":\"true\"}}},\"titleWrap\":{\"expr\":{\"Literal\":{\"Value\":\"true\"}}},\"alignment\":{\"expr\":{\"Literal\":{\"Value\":\"'center'\"}}},\"fontSize\":{\"expr\":{\"Literal\":{\"Value\":\"18D\"}}},\"bold\":{\"expr\":{\"Literal\":{\"Value\":\"true\"}}}}}],\"background\":[{\"properties\":{\"show\":{\"expr\":{\"Literal\":{\"Value\":\"true\"}}},\"transparency\":{\"expr\":{\"Literal\":{\"Value\":\"0D\"}}}}}],\"border\":[{\"properties\":{\"width\":{\"expr\":{\"Literal\":{\"Value\":\"1D\"}}}}}]}}}",
          "filters": "[]",
          "height": 111.50,
          "width": 508.35,
          "x": 9.45,
          "y": 39.69,
          "z": 1000.00
        },
        {
          "config": "{\"name\":\"b031118409ac753791c1\",\"layouts\":[{\"id\":0,\"position\":{\"x\":9.448891554591802,\"y\":151.18226487346882,\"z\":0,\"width\":1269.9310249371383,\"height\":568.8232715864265,\"tabOrder\":0}}],\"singleVisual\":{\"visualType\":\"map\",\"projections\":{\"Y\":[{\"queryRef\":\"earthquake_events_gold.latitude\"}],\"X\":[{\"queryRef\":\"earthquake_events_gold.longitude\"}],\"Series\":[{\"queryRef\":\"earthquake_events_gold.sig_class\"}]},\"prototypeQuery\":{\"Version\":2,\"From\":[{\"Name\":\"e\",\"Entity\":\"earthquake_events_gold\",\"Type\":0}],\"Select\":[{\"Column\":{\"Expression\":{\"SourceRef\":{\"Source\":\"e\"}},\"Property\":\"latitude\"},\"Name\":\"earthquake_events_gold.latitude\",\"NativeReferenceName\":\"latitude\"},{\"Column\":{\"Expression\":{\"SourceRef\":{\"Source\":\"e\"}},\"Property\":\"longitude\"},\"Name\":\"earthquake_events_gold.longitude\",\"NativeReferenceName\":\"longitude\"},{\"Column\":{\"Expression\":{\"SourceRef\":{\"Source\":\"e\"}},\"Property\":\"sig_class\"},\"Name\":\"earthquake_events_gold.sig_class\",\"NativeReferenceName\":\"sig_class\"}]},\"drillFilterOtherVisuals\":true,\"objects\":{\"mapStyles\":[{\"properties\":{\"mapTheme\":{\"expr\":{\"Literal\":{\"Value\":\"'aerial'\"}}},\"showLabels\":{\"expr\":{\"Literal\":{\"Value\":\"true\"}}}}}],\"mapControls\":[{\"properties\":{\"showLassoButton\":{\"expr\":{\"Literal\":{\"Value\":\"false\"}}}}}],\"bubbles\":[{\"properties\":{\"bubbleSize\":{\"expr\":{\"Literal\":{\"Value\":\"3L\"}}}}}],\"legend\":[{\"properties\":{\"position\":{\"expr\":{\"Literal\":{\"Value\":\"'Top'\"}}},\"fontSize\":{\"expr\":{\"Literal\":{\"Value\":\"10D\"}}}}}],\"categoryLabels\":[{\"properties\":{\"show\":{\"expr\":{\"Literal\":{\"Value\":\"false\"}}}}}]},\"vcObjects\":{\"title\":[{\"properties\":{\"text\":{\"expr\":{\"Literal\":{\"Value\":\"'Earthquake Map'\"}}},\"heading\":{\"expr\":{\"Literal\":{\"Value\":\"'Heading2'\"}}},\"fontSize\":{\"expr\":{\"Literal\":{\"Value\":\"17D\"}}},\"bold\":{\"expr\":{\"Literal\":{\"Value\":\"true\"}}},\"italic\":{\"expr\":{\"Literal\":{\"Value\":\"false\"}}},\"underline\":{\"expr\":{\"Literal\":{\"Value\":\"false\"}}},\"alignment\":{\"expr\":{\"Literal\":{\"Value\":\"'center'\"}}}}}]}}}",
          "filters": "[]",
          "height": 568.82,
          "width": 1269.93,
          "x": 9.45,
          "y": 151.18,
          "z": 0.00
        },
        {
          "config": "{\"name\":\"d3040bd83b20c43b02d0\",\"layouts\":[{\"id\":0,\"position\":{\"x\":771.029550854691,\"y\":39.68534452928557,\"z\":2000,\"width\":508.350365637039,\"height\":111.49692034418327,\"tabOrder\":2000}}],\"singleVisual\":{\"visualType\":\"slicer\",\"projections\":{\"Values\":[{\"queryRef\":\"earthquake_events_gold.country_code\",\"active\":true}]},\"prototypeQuery\":{\"Version\":2,\"From\":[{\"Name\":\"e\",\"Entity\":\"earthquake_events_gold\",\"Type\":0}],\"Select\":[{\"Column\":{\"Expression\":{\"SourceRef\":{\"Source\":\"e\"}},\"Property\":\"country_code\"},\"Name\":\"earthquake_events_gold.country_code\",\"NativeReferenceName\":\"country_code\"}]},\"drillFilterOtherVisuals\":true,\"objects\":{\"data\":[{\"properties\":{\"mode\":{\"expr\":{\"Literal\":{\"Value\":\"'Dropdown'\"}}}}}],\"header\":[{\"properties\":{\"text\":{\"expr\":{\"Literal\":{\"Value\":\"'Country'\"}}},\"show\":{\"expr\":{\"Literal\":{\"Value\":\"false\"}}}}}],\"general\":[{\"properties\":{\"orientation\":{\"expr\":{\"Literal\":{\"Value\":\"1D\"}}}}}]},\"vcObjects\":{\"title\":[{\"properties\":{\"show\":{\"expr\":{\"Literal\":{\"Value\":\"true\"}}},\"titleWrap\":{\"expr\":{\"Literal\":{\"Value\":\"true\"}}},\"alignment\":{\"expr\":{\"Literal\":{\"Value\":\"'center'\"}}},\"fontSize\":{\"expr\":{\"Literal\":{\"Value\":\"18D\"}}},\"bold\":{\"expr\":{\"Literal\":{\"Value\":\"true\"}}},\"text\":{\"expr\":{\"Literal\":{\"Value\":\"'Country Code'\"}}}}}],\"background\":[{\"properties\":{\"show\":{\"expr\":{\"Literal\":{\"Value\":\"true\"}}},\"transparency\":{\"expr\":{\"Literal\":{\"Value\":\"0D\"}}}}}],\"border\":[{\"properties\":{\"width\":{\"expr\":{\"Literal\":{\"Value\":\"1D\"}}}}}]}}}",
          "filters": "[]",
          "height": 111.50,
          "width": 508.35,
          "x": 771.03,
          "y": 39.69,
          "z": 2000.00
        },
        {
          "config": "{\"name\":\"fab5242051c10301e137\",\"layouts\":[{\"id\":0,\"position\":{\"x\":517.7992571916308,\"y\":39.68534452928557,\"z\":3000,\"width\":253.2302936630603,\"height\":111.49692034418327,\"tabOrder\":3000}}],\"singleVisual\":{\"visualType\":\"slicer\",\"projections\":{\"Values\":[{\"queryRef\":\"earthquake_events_gold.sig_class\",\"active\":true}]},\"prototypeQuery\":{\"Version\":2,\"From\":[{\"Name\":\"e\",\"Entity\":\"earthquake_events_gold\",\"Type\":0}],\"Select\":[{\"Column\":{\"Expression\":{\"SourceRef\":{\"Source\":\"e\"}},\"Property\":\"sig_class\"},\"Name\":\"earthquake_events_gold.sig_class\",\"NativeReferenceName\":\"sig_class\"}]},\"drillFilterOtherVisuals\":true,\"objects\":{\"data\":[{\"properties\":{\"mode\":{\"expr\":{\"Literal\":{\"Value\":\"'Dropdown'\"}}}}}],\"general\":[{\"properties\":{\"orientation\":{\"expr\":{\"Literal\":{\"Value\":\"1D\"}}},\"filter\":{\"filter\":{\"Version\":2,\"From\":[{\"Name\":\"e\",\"Entity\":\"earthquake_events_gold\",\"Type\":0}],\"Where\":[{\"Condition\":{\"In\":{\"Expressions\":[{\"Column\":{\"Expression\":{\"SourceRef\":{\"Source\":\"e\"}},\"Property\":\"sig_class\"}}],\"Values\":[[{\"Literal\":{\"Value\":\"'High'\"}}]]}}}]}}}}],\"header\":[{\"properties\":{\"show\":{\"expr\":{\"Literal\":{\"Value\":\"false\"}}}}}]},\"vcObjects\":{\"title\":[{\"properties\":{\"show\":{\"expr\":{\"Literal\":{\"Value\":\"true\"}}},\"text\":{\"expr\":{\"Literal\":{\"Value\":\"'Magnitude Significance'\"}}},\"fontSize\":{\"expr\":{\"Literal\":{\"Value\":\"18D\"}}},\"bold\":{\"expr\":{\"Literal\":{\"Value\":\"true\"}}},\"alignment\":{\"expr\":{\"Literal\":{\"Value\":\"'center'\"}}}}}]}}}",
          "filters": "[]",
          "height": 111.50,
          "width": 253.23,
          "x": 517.80,
          "y": 39.69,
          "z": 3000.00
        },
        {
          "config": "{\"name\":\"fb4cbd3f1ce278599077\",\"layouts\":[{\"id\":0,\"position\":{\"x\":517.7992571916308,\"y\":0,\"z\":4000,\"width\":272.1280767722439,\"height\":39.68534452928557,\"tabOrder\":4000}}],\"singleVisual\":{\"visualType\":\"textbox\",\"drillFilterOtherVisuals\":true,\"objects\":{\"general\":[{\"properties\":{\"paragraphs\":[{\"textRuns\":[{\"value\":\"Earthquake Data\",\"textStyle\":{\"fontFamily\":\"Arial Black\",\"fontSize\":\"16pt\",\"color\":\"#e8d166\"}}],\"horizontalTextAlignment\":\"center\"}]}}]},\"vcObjects\":{\"title\":[{\"properties\":{\"show\":{\"expr\":{\"Literal\":{\"Value\":\"true\"}}},\"titleWrap\":{\"expr\":{\"Literal\":{\"Value\":\"true\"}}},\"alignment\":{\"expr\":{\"Literal\":{\"Value\":\"'center'\"}}},\"fontSize\":{\"expr\":{\"Literal\":{\"Value\":\"18D\"}}},\"bold\":{\"expr\":{\"Literal\":{\"Value\":\"true\"}}}}}],\"background\":[{\"properties\":{\"show\":{\"expr\":{\"Literal\":{\"Value\":\"true\"}}},\"transparency\":{\"expr\":{\"Literal\":{\"Value\":\"0D\"}}}}}],\"border\":[{\"properties\":{\"width\":{\"expr\":{\"Literal\":{\"Value\":\"1D\"}}}}}]}}}",
          "filters": "[]",
          "height": 39.69,
          "width": 272.13,
          "x": 517.80,
          "y": 0.00,
          "z": 4000.00
        }
      ],
      "width": 1280.00
    }
  ]
}